python_opendota/__init__.py
python_opendota/api/__init__.py
python_opendota/api/benchmarks_api.py
python_opendota/api/constants_api.py
python_opendota/api/distributions_api.py
python_opendota/api/explorer_api.py
python_opendota/api/find_matches_api.py
python_opendota/api/health_api.py
python_opendota/api/hero_stats_api.py
python_opendota/api/heroes_api.py
python_opendota/api/leagues_api.py
python_opendota/api/live_api.py
python_opendota/api/matches_api.py
python_opendota/api/metadata_api.py
python_opendota/api/parsed_matches_api.py
python_opendota/api/players_api.py
python_opendota/api/players_by_rank_api.py
python_opendota/api/pro_matches_api.py
python_opendota/api/pro_players_api.py
python_opendota/api/public_matches_api.py
python_opendota/api/rankings_api.py
python_opendota/api/records_api.py
python_opendota/api/replays_api.py
python_opendota/api/request_api.py
python_opendota/api/scenarios_api.py
python_opendota/api/schema_api.py
python_opendota/api/search_api.py
python_opendota/api/status_api.py
python_opendota/api/teams_api.py
python_opendota/api_client.py
python_opendota/apis/__init__.py
python_opendota/configuration.py
python_opendota/exceptions.py
python_opendota/model/__init__.py
python_opendota/model/benchmarks_response.py
python_opendota/model/benchmarks_response_result.py
python_opendota/model/benchmarks_response_result_gold_per_min.py
python_opendota/model/distributions_response.py
python_opendota/model/distributions_response_country_mmr.py
python_opendota/model/distributions_response_country_mmr_fields.py
python_opendota/model/distributions_response_country_mmr_rows.py
python_opendota/model/distributions_response_mmr.py
python_opendota/model/distributions_response_ranks.py
python_opendota/model/distributions_response_ranks_fields.py
python_opendota/model/distributions_response_ranks_rows.py
python_opendota/model/distributions_response_ranks_sum.py
python_opendota/model/hero_durations_response.py
python_opendota/model/hero_item_popularity_response.py
python_opendota-1.0.2.dist-info/LICENSE
python_opendota-1.0.2.dist-info/WHEEL
python_opendota-1.0.2.dist-info/METADATA
python_opendota-1.0.2.dist-info/RECORD
