Metadata-Version: 2.1
Name: python-opendota
Version: 1.0.2
Summary: Generated Python SDK for working with OpenDota API
Home-page: https://docs.opendota.com/
License: Apache-2.0
Keywords: OpenAPI,OpenAPI-Generator,OpenDota API
Author: OpenAPI Generator community
Author-email: team@openapitools.org
Maintainer: Dmitry Vasiliev
Maintainer-email: contact.vasiliev.dmitry@gmail.com
Requires-Python: >=3.6,<4
Classifier: License :: OSI Approved :: Apache Software License
Classifier: Operating System :: OS Independent
Classifier: Programming Language :: Python :: 3
Classifier: Programming Language :: Python :: 3.10
Classifier: Programming Language :: Python :: 3.6
Classifier: Programming Language :: Python :: 3.7
Classifier: Programming Language :: Python :: 3.8
Classifier: Programming Language :: Python :: 3.9
Requires-Dist: python-dateutil (>=2.8.2,<3.0.0)
Requires-Dist: urllib3 (>=1.26.9,<2.0.0)
Project-URL: Documentation, https://github.com/swimmwatch/python-opendota#documentation-for-api-endpoints
Project-URL: Repository, https://github.com/swimmwatch/python-opendota
